squelette/VERSION
squelette/__init__.py
squelette/data/python/.gitignore
squelette/data/python/LICENSE.txt
squelette/data/python/README.rst
squelette/data/python/setup.cfg
squelette/data/python/setup.py
squelette/data/python/tox.ini
squelette/data/python/0/build.sh
squelette/data/python/0/clean.sh
squelette/data/python/0/ipython_config.py
squelette/data/python/0/make_venv2.sh
squelette/data/python/0/make_venv3.sh
squelette/data/python/0/register.sh
squelette/data/python/0/test_upload.sh
squelette/data/python/0/upload.sh
squelette/data/python/bin/hello-template
squelette/data/python/template/VERSION
squelette/data/python/template/__init__.py
squelette/data/python/template/template.py
squelette/data/python/tests/test_template
squelette-0.0.9.data/scripts/squelette
squelette-0.0.9.dist-info/LICENSE.txt
squelette-0.0.9.dist-info/METADATA
squelette-0.0.9.dist-info/WHEEL
squelette-0.0.9.dist-info/top_level.txt
squelette-0.0.9.dist-info/RECORD
