Metadata-Version: 2.1
Name: squelette
Version: 0.0.9
Summary: squelette - skeleton generator
Home-page: http://appliedstochastics.com
Author: Ajay Khanna
Author-email: 
License: MIT
Platform: UNKNOWN
Provides-Extra: dev
Requires-Dist: pytest ; extra == 'dev'
Requires-Dist: tox ; extra == 'dev'
